ds_opencc/__init__.py
ds_opencc/clib/__init__.py
ds_opencc/clib/opencc_clib.cpython-311-x86_64-linux-gnu.so
ds_opencc/clib/share/opencc/HKVariants.ocd2
ds_opencc/clib/share/opencc/HKVariantsRev.ocd2
ds_opencc/clib/share/opencc/HKVariantsRevPhrases.ocd2
ds_opencc/clib/share/opencc/JPShinjitaiCharacters.ocd2
ds_opencc/clib/share/opencc/JPShinjitaiPhrases.ocd2
ds_opencc/clib/share/opencc/JPVariants.ocd2
ds_opencc/clib/share/opencc/JPVariantsRev.ocd2
ds_opencc/clib/share/opencc/STCharacters.ocd2
ds_opencc/clib/share/opencc/STPhrases.ocd2
ds_opencc/clib/share/opencc/TSCharacters.ocd2
ds_opencc/clib/share/opencc/TSPhrases.ocd2
ds_opencc/clib/share/opencc/TWPhrases.ocd2
ds_opencc/clib/share/opencc/TWPhrasesRev.ocd2
ds_opencc/clib/share/opencc/TWVariants.ocd2
ds_opencc/clib/share/opencc/TWVariantsRev.ocd2
ds_opencc/clib/share/opencc/TWVariantsRevPhrases.ocd2
ds_opencc/clib/share/opencc/hk2s.json
ds_opencc/clib/share/opencc/hk2t.json
ds_opencc/clib/share/opencc/jp2t.json
ds_opencc/clib/share/opencc/s2hk.json
ds_opencc/clib/share/opencc/s2t.json
ds_opencc/clib/share/opencc/s2tw.json
ds_opencc/clib/share/opencc/s2twp.json
ds_opencc/clib/share/opencc/t2hk.json
ds_opencc/clib/share/opencc/t2jp.json
ds_opencc/clib/share/opencc/t2s.json
ds_opencc/clib/share/opencc/t2tw.json
ds_opencc/clib/share/opencc/tw2s.json
ds_opencc/clib/share/opencc/tw2sp.json
ds_opencc/clib/share/opencc/tw2t.json
ds_opencc-1.1.11.dist-info/AUTHORS
ds_opencc-1.1.11.dist-info/LICENSE
ds_opencc-1.1.11.dist-info/METADATA
ds_opencc-1.1.11.dist-info/WHEEL
ds_opencc-1.1.11.dist-info/top_level.txt
ds_opencc-1.1.11.dist-info/RECORD
